kra_etims/__init__.py
kra_etims/api.py
kra_etims-1.0.1.dist-info/LICENSE.txt
kra_etims-1.0.1.dist-info/METADATA
kra_etims-1.0.1.dist-info/WHEEL
kra_etims-1.0.1.dist-info/top_level.txt
kra_etims-1.0.1.dist-info/RECORD
