Metadata-Version: 2.1
Name: kra-etims
Version: 1.0.1
Summary: A Python wrapper for the KRA eTIMS REST API
Home-page: https://github.com/ingenious-dev/kra-etims-api-python
Author: Joseph Suhudu @ ingenious.or.ke
Author-email: suhudu+joseph@gmail.com
License: MIT License
Project-URL: Source, https://github.com/ingenious-dev/kra-etims-api-python
Project-URL: Tracker, https://github.com/ingenious-dev/kra-etims-api-python/issues
Keywords: kra etims rest api
Platform: any
Classifier: Development Status :: 5 - Production/Stable
Classifier: Intended Audience :: Developers
Classifier: Natural Language :: English
Classifier: License :: OSI Approved :: MIT License
Classifier: Programming Language :: Python
Classifier: Programming Language :: Python :: 3.6
Classifier: Programming Language :: Python :: 3.7
Classifier: Programming Language :: Python :: 3.8
Classifier: Programming Language :: Python :: 3.9
Classifier: Topic :: Software Development :: Libraries :: Python Modules
Requires-Python: >=3.6
License-File: LICENSE.txt
Requires-Dist: requests
